Tool.py
sztestlib/__init__.py
sztestlib/szlibone.py
wc001-1.0.0.dist-info/LICENSE.txt
wc001-1.0.0.dist-info/METADATA
wc001-1.0.0.dist-info/WHEEL
wc001-1.0.0.dist-info/top_level.txt
wc001-1.0.0.dist-info/RECORD
