Metadata-Version: 2.1
Name: wc001
Version: 1.0.0
Summary: 王聪的第一个自建库
Home-page: UNKNOWN
Author: Sz
Author-email: wangshu10@chinaunicom.cn
License: MIT
Platform: UNKNOWN
License-File: LICENSE.txt
